mailtmwrapper/MailTmWrapper.py
mailtmwrapper/__init__.py
MailTmWrapper-0.0.6.dist-info/LICENSE
MailTmWrapper-0.0.6.dist-info/METADATA
MailTmWrapper-0.0.6.dist-info/WHEEL
MailTmWrapper-0.0.6.dist-info/top_level.txt
MailTmWrapper-0.0.6.dist-info/RECORD
