Metadata-Version: 2.2
Name: MailTmWrapper
Version: 0.0.6
Summary: A Python wrapper for the Mail.tm API
Home-page: https://github.com/sexfrance/MailTM-Wrapper
Author: Sexfrance
Author-email: bwuuuuu@gmail.com
Classifier: Programming Language :: Python :: 3
Classifier: License :: OSI Approved :: MIT License
Classifier: Operating System :: OS Independent
Classifier: Development Status :: 3 - Alpha
Classifier: Intended Audience :: Developers
Classifier: Topic :: Communications :: Email
Requires-Python: >=3.6
License-File: LICENSE
Requires-Dist: requests
Dynamic: author
Dynamic: author-email
Dynamic: classifier
Dynamic: description
Dynamic: description-content-type
Dynamic: home-page
Dynamic: requires-dist
Dynamic: requires-python
Dynamic: summary
